{
  "Version": "3.3.0", 
  "Began": "Wed Mar 13 11:02:27 2024", 
  "Command line": "ior -a MPIIO -l timestamp -g -G -1401473791 -k -e -i 1 -s 1 -b 21474836480 -t 2097152 -o /beeond/0/test_file -O summaryFormat=JSON -O summaryFile=/work/0/NBB/hiraga/work/mpiio-pmembb/raw/ior-beeond/2024.03.13-11.01.27-default/2024.03.13-11.02.20-182871.nqsv-32/ior_summary_0.json -w", 
  "Machine": "Linux bnode031", 
  "tests": [
    {
    "TestID": 0, 
    "StartTime": "Wed Mar 13 11:02:27 2024"    , "Path": "/beeond/0","Capacity": "61.5 TiB", "Used Capacity": "5.1%","Inodes": "0.0 Mi", "Used Inodes" : "-nan%"
, 
    "Parameters": {
      "testID": 0, 
      "refnum": 0, 
      "api": "MPIIO", 
      "platform": "bnode(Linux)", 
      "testFileName": "/beeond/0/test_file", 
      "hintsFileName": "(null)", 
      "deadlineForStonewall": 0, 
      "stoneWallingWearOut": 0, 
      "maxTimeDuration": 0, 
      "outlierThreshold": 0, 
      "options": "(null)", 
      "dryRun": 0, 
      "nodes": 32, 
      "memoryPerTask": 0, 
      "memoryPerNode": 0, 
      "tasksPerNode": 16, 
      "repetitions": 1, 
      "multiFile": 0, 
      "interTestDelay": 0, 
      "fsync": 1, 
      "fsyncperwrite": 0, 
      "useExistingTestFile": 0, 
      "showHints": 0, 
      "uniqueDir": 0, 
      "individualDataSets": 0, 
      "singleXferAttempt": 0, 
      "readFile": 0, 
      "writeFile": 1, 
      "filePerProc": 0, 
      "reorderTasks": 0, 
      "reorderTasksRandom": 0, 
      "reorderTasksRandomSeed": 0, 
      "randomOffset": 0, 
      "checkWrite": 0, 
      "checkRead": 0, 
      "preallocate": 0, 
      "useFileView": 0, 
      "setAlignment": 1, 
      "storeFileOffset": 0, 
      "useSharedFilePointer": 0, 
      "useStridedDatatype": 0, 
      "keepFile": 1, 
      "keepFileWithError": 0, 
      "quitOnError": 0, 
      "verbose": 0, 
      "data packet type": "t", 
      "setTimeStampSignature/incompressibleSeed": -1401473791, 
      "collective": 0, 
      "segmentCount": 1, 
      "transferSize": 2097152, 
      "blockSize": 21474836480
    }
, 
    "Options": {
      "api": "MPIIO", 
      "apiVersion": "(3.1)", 
      "test filename": "/beeond/0/test_file", 
      "access": "single-shared-file", 
      "type": "independent", 
      "segments": 1, 
      "ordering in a file": "sequential", 
      "ordering inter file": "no tasks offsets", 
      "nodes": 32, 
      "tasks": 512, 
      "clients per node": 16, 
      "repetitions": 1, 
      "xfersize": "2 MiB", 
      "blocksize": "20 GiB", 
      "aggregate filesize": "10 TiB"
    }
, 
    "Results": [
      [             {
        "access": "write", 
        "bwMiB": 67307.8472, 
        "blockKiB": 20971520.0000, 
        "xferKiB": 2048.0000, 
        "iops": 33742.4299, 
        "latency": 0.0150, 
        "openTime": 0.4003, 
        "wrRdTime": 155.3794, 
        "closeTime": 0.0091, 
        "totalTime": 155.7881
      }
]
]
, 
  "max": {
    "writeMiB": 67307.8472, 
    "writeMB": 70577.3932
  }

}
]
, 
"summary": [
{
  "operation": "write", 
  "API": "MPIIO", 
  "TestID": 0, 
  "ReferenceNumber": 0, 
  "segmentCount": 1, 
  "blockSize": 21474836480, 
  "transferSize": 2097152, 
  "numTasks": 512, 
  "tasksPerNode": 16, 
  "repetitions": 1, 
  "filePerProc": 0, 
  "reorderTasks": 0, 
  "taskPerNodeOffset": 1, 
  "reorderTasksRandom": 0, 
  "reorderTasksRandomSeed": 0, 
  "segmentCount": 1, 
  "blockSize": 21474836480, 
  "transferSize": 2097152, 
  "bwMaxMIB": 67307.8472, 
  "bwMinMIB": 67307.8472, 
  "bwMeanMIB": 67307.8472, 
  "bwStdMIB": 0.0000, 
  "OPsMax": 33653.9236, 
  "OPsMin": 33653.9236, 
  "OPsMean": 33653.9236, 
  "OPsSD": 0.0000, 
  "MeanTime": 155.7881, 
  "xsizeMiB": 10485760.0000
}
]
, 
"Finished": "Wed Mar 13 11:05:23 2024"
}
