{
  "Version": "3.3.0", 
  "Began": "Sun Mar 10 12:48:38 2024", 
  "Command line": "ior -a MPIIO -l timestamp -g -G -1401473791 -k -e -i 1 -s 1 -b 8589934592 -t 2097152 -o /beeond/0/test_file -O summaryFormat=JSON -O summaryFile=/work/0/NBB/hiraga/work/mpiio-pmembb/raw/ior-beeond/2024.03.10-12.43.26-1-64/2024.03.10-12.48.29-182329.nqsv-16/ior_summary_0.json -w", 
  "Machine": "Linux bnode075", 
  "tests": [
    {
    "TestID": 0, 
    "StartTime": "Sun Mar 10 12:48:38 2024"    , "Path": "/beeond/0","Capacity": "30.7 TiB", "Used Capacity": "5.1%","Inodes": "0.0 Mi", "Used Inodes" : "-nan%"
, 
    "Parameters": {
      "testID": 0, 
      "refnum": 0, 
      "api": "MPIIO", 
      "platform": "bnode(Linux)", 
      "testFileName": "/beeond/0/test_file", 
      "hintsFileName": "(null)", 
      "deadlineForStonewall": 0, 
      "stoneWallingWearOut": 0, 
      "maxTimeDuration": 0, 
      "outlierThreshold": 0, 
      "options": "(null)", 
      "dryRun": 0, 
      "nodes": 16, 
      "memoryPerTask": 0, 
      "memoryPerNode": 0, 
      "tasksPerNode": 16, 
      "repetitions": 1, 
      "multiFile": 0, 
      "interTestDelay": 0, 
      "fsync": 1, 
      "fsyncperwrite": 0, 
      "useExistingTestFile": 0, 
      "showHints": 0, 
      "uniqueDir": 0, 
      "individualDataSets": 0, 
      "singleXferAttempt": 0, 
      "readFile": 0, 
      "writeFile": 1, 
      "filePerProc": 0, 
      "reorderTasks": 0, 
      "reorderTasksRandom": 0, 
      "reorderTasksRandomSeed": 0, 
      "randomOffset": 0, 
      "checkWrite": 0, 
      "checkRead": 0, 
      "preallocate": 0, 
      "useFileView": 0, 
      "setAlignment": 1, 
      "storeFileOffset": 0, 
      "useSharedFilePointer": 0, 
      "useStridedDatatype": 0, 
      "keepFile": 1, 
      "keepFileWithError": 0, 
      "quitOnError": 0, 
      "verbose": 0, 
      "data packet type": "t", 
      "setTimeStampSignature/incompressibleSeed": -1401473791, 
      "collective": 0, 
      "segmentCount": 1, 
      "transferSize": 2097152, 
      "blockSize": 8589934592
    }
, 
    "Options": {
      "api": "MPIIO", 
      "apiVersion": "(3.1)", 
      "test filename": "/beeond/0/test_file", 
      "access": "single-shared-file", 
      "type": "independent", 
      "segments": 1, 
      "ordering in a file": "sequential", 
      "ordering inter file": "no tasks offsets", 
      "nodes": 16, 
      "tasks": 256, 
      "clients per node": 16, 
      "repetitions": 1, 
      "xfersize": "2 MiB", 
      "blocksize": "8 GiB", 
      "aggregate filesize": "2 TiB"
    }
, 
    "Results": [
      [             {
        "access": "write", 
        "bwMiB": 33832.5534, 
        "blockKiB": 8388608.0000, 
        "xferKiB": 2048.0000, 
        "iops": 16986.5570, 
        "latency": 0.0149, 
        "openTime": 0.2541, 
        "wrRdTime": 61.7298, 
        "closeTime": 0.0033, 
        "totalTime": 61.9862
      }
]
]
, 
  "max": {
    "writeMiB": 33832.5534, 
    "writeMB": 35476.0035
  }

}
]
, 
"summary": [
{
  "operation": "write", 
  "API": "MPIIO", 
  "TestID": 0, 
  "ReferenceNumber": 0, 
  "segmentCount": 1, 
  "blockSize": 8589934592, 
  "transferSize": 2097152, 
  "numTasks": 256, 
  "tasksPerNode": 16, 
  "repetitions": 1, 
  "filePerProc": 0, 
  "reorderTasks": 0, 
  "taskPerNodeOffset": 1, 
  "reorderTasksRandom": 0, 
  "reorderTasksRandomSeed": 0, 
  "segmentCount": 1, 
  "blockSize": 8589934592, 
  "transferSize": 2097152, 
  "bwMaxMIB": 33832.5534, 
  "bwMinMIB": 33832.5534, 
  "bwMeanMIB": 33832.5534, 
  "bwStdMIB": 0.0000, 
  "OPsMax": 16916.2767, 
  "OPsMin": 16916.2767, 
  "OPsMean": 16916.2767, 
  "OPsSD": 0.0000, 
  "MeanTime": 61.9862, 
  "xsizeMiB": 2097152.0000
}
]
, 
"Finished": "Sun Mar 10 12:50:00 2024"
}
